Metadata-Version: 1.1
Name: long-log
Version: 0.0.2
Summary: eee
Home-page: https://gitee.com/zhenzi0322_admin/long_log
Author: zhenzi
Author-email: 82131529@qq.com
License: UNKNOWN
Platform: UNKNOWN
Classifier: Programming Language :: Python :: 3.7
Classifier: Operating System :: MacOS :: MacOS X
Classifier: Operating System :: POSIX :: Linux
